skylite/__init__.py
skylite/exchange.py
skylite/project.py
skylite/store.py
skylite/utils.py
skylite-0.2.dist-info/licenses/LICENSE.txt
skylite-0.2.dist-info/METADATA
skylite-0.2.dist-info/WHEEL
skylite-0.2.dist-info/top_level.txt
skylite-0.2.dist-info/RECORD
