Metadata-Version: 2.4
Name: skylite
Version: 0.2
Summary: Manage model artifacts throughout the model development process.
Author-email: "Jesse C. Sealand" <jesse.sealand@outlook.com>
Project-URL: Homepage, https://github.com/jesse-sealand/skylite
Project-URL: Bug Tracker, https://github.com/jesse-sealand/skylite/issues
Keywords: python,modeling,model-development,organization-tool
Classifier: Programming Language :: Python :: 3
Classifier: License :: OSI Approved :: MIT License
Classifier: Operating System :: OS Independent
Requires-Python: >=3.12
License-File: LICENSE.txt
Dynamic: license-file
